[
  {
    "id": "_meta",
    "author": "Dungeon Mister",
    "name": "Blending In",
    "colour": "#0a6621",
    "logo": "https://bloodontheclocktower.com/cdn/shop/files/2_-_Logo_-_Skull_GOS-edit_2.png?v=1761821562&width=1070"
  },
  "steward",
  "librarian",
  "pixie",
  "bountyhunter",
  "highpriestess",
  "chambermaid",
  "towncrier",
  "undertaker",
  "nightwatchman",
  "seamstress",
  "juggler",
  "farmer",
  "magician",
  "drunk",
  "plaguedoctor",
  "mutant",
  "politician",
  "poisoner",
  "xaan",
  "scarletwoman",
  "boffin",
  "imp",
  "spiritofivory",
  "sentinel"
]
